llama_index/embeddings/netmind/__init__.py
llama_index/embeddings/netmind/base.py
llama_index_embeddings_netmind-0.2.1.dist-info/METADATA
llama_index_embeddings_netmind-0.2.1.dist-info/WHEEL
llama_index_embeddings_netmind-0.2.1.dist-info/licenses/LICENSE
llama_index_embeddings_netmind-0.2.1.dist-info/RECORD
